tryhot/tryhot.py
tryhot-0.1.0.dist-info/METADATA
tryhot-0.1.0.dist-info/WHEEL
tryhot-0.1.0.dist-info/top_level.txt
tryhot-0.1.0.dist-info/RECORD
